freshdesk_mcp/__init__.py
freshdesk_mcp/server.py
freshdesk_mcp-1.2.0.dist-info/METADATA
freshdesk_mcp-1.2.0.dist-info/WHEEL
freshdesk_mcp-1.2.0.dist-info/entry_points.txt
freshdesk_mcp-1.2.0.dist-info/licenses/LICENSE
freshdesk_mcp-1.2.0.dist-info/RECORD
