Metadata-Version: 2.4
Name: freshdesk-mcp
Version: 1.2.0
Summary: An MCP server for Freshdesk
Author-email: Gopi Krishnan <gopi@effy.co.in>, Maanaesh Swamy <maanaesh.s@effy.co.in>
License-File: LICENSE
Requires-Python: >=3.10
Requires-Dist: build>=1.2.2.post1
Requires-Dist: httpx==0.28.1
Requires-Dist: mcp[cli]>=1.3.0
Requires-Dist: pydantic>=2.10.6
